{
    "base_config": "config/vits.json",
    "model_type": "VITSSVC",
    "dataset": [
        "m4singer",
        "opencpop",
        "opensinger",
        "svcc",
        "vctk"
    ],
    "dataset_path": {
        // TODO: Fill in your dataset path
        "m4singer": "[M4Singer dataset path]",
        "opencpop": "[Opencpop dataset path]",
        "opensinger": "[OpenSinger dataset path]",
        "svcc": "[SVCC dataset path]",
        "vctk": "[VCTK dataset path]"
    },
    // TODO: Fill in the output log path. The default value is "Amphion/ckpts/svc"
    "log_dir": "ckpts/svc",
    "preprocess": {
        // TODO: Fill in the output data path. The default value is "Amphion/data"
        "processed_dir": "data",
        
        "f0_min": 50,
        "f0_max": 1100,
        // f0_bin in sovits
        "pitch_bin": 256,
        // filter_length in sovits
        "n_fft": 2048,
        // hop_length in sovits
        "hop_size": 512,
        // win_length in sovits
        "win_size": 2048,

        "use_text": false,
        "use_phone": false,

        // Config for features extraction
        "extract_mel": true,
        "extract_pitch": true,
        "extract_energy": true,
        "pitch_extractor": "parselmouth",
        "extract_uv": true,
        "extract_contentvec_feature": true,
        "contentvec_sample_rate": 16000,
        "contentvec_batch_size": 1,
        // Fill in the content-based pretrained model's path
        "contentvec_file": "pretrained/contentvec/checkpoint_best_legacy_500.pt",
        // Config for features usage
        "use_mel": true,
        "use_frame_pitch": true,
        "use_uv": true,
        "uv_dir": "uvs", // directory name of extracted unvoiced features
        "use_spkid": true,
        "use_contentvec": true,
        "n_mel": 100,
        "sample_rate": 24000,
        
        // min_max_norm_mel
        // "mel_min_max_norm": true,
        // "mel_min_max_stats_dir": "mel_min_max_stats",
        // "use_min_max_norm_mel": true,

        // Extract content features using dataloader
        "pin_memory": true,
        "num_workers": 8,
        "content_feature_batch_size": 16,
        // Default config for content vector
        "contentvec_frameshift": 0.02,
        // Meta file
        "train_file": "train.json",
        "valid_file": "test.json",
        "spk2id": "singers.json",
        "utt2spk": "utt2singer"
    },
    "model": {
        "condition_encoder": {
            // Config for features usage
            "use_contentvec": true,
            "use_whisper": false,
            "use_mert": false,
            "use_wenet": false,
            "whisper_dim": 1024,
            "contentvec_dim": 256,
            "wenet_dim": 512,
            "use_singer_encoder": false,
            "pitch_min": 50,
            "pitch_max": 1100,
        },
        "vits": {
            "inter_channels": 192,
            "hidden_channels": 192,
            "filter_channels": 256,
            "n_heads": 2,
            "n_layers": 6,
            "kernel_size": 3,
            "p_dropout": 0.1,
            "ssl_dim": 256,
            "n_flow_layer": 4,
            "n_layers_q": 3,
            "gin_channels": 256,
            "n_speakers": 512,
        },
        "generator": "hifigan",
        "hifigan": {
            "resblock": "1",
            "resblock_kernel_sizes": [
              3,
              7,
              11
            ],
            "upsample_rates": [
              8,8,2,2,2
            ],
            "upsample_kernel_sizes": [
              16,16,4,4,4
            ],
            "upsample_initial_channel": 512,
            "resblock_dilation_sizes": [
                [1,3,5],
                [1,3,5],
                [1,3,5]
            ]
        },
    },
    "train": {
        "batch_size": 32,
        "gradient_accumulation_step": 1,
        "max_epoch": -1, // -1 means no limit
        "save_checkpoint_stride": [
            3,
            50
        ],
        "keep_last": [
            3,
            2
        ],
        "run_eval": [
            true,
            true
        ],
        "adamw": {
            "lr": 2.0e-4
        },
        "reducelronplateau": {
            "factor": 0.8,
            "patience": 30,
            "min_lr": 1.0e-4
        },
        "dataloader": {
            "num_worker": 8,
            "pin_memory": true
        },
        "sampler": {
            "holistic_shuffle": false,
            "drop_last": true
        }
    },
    "inference": {
        "batch_size": 1,
    }
}